boldsign/__init__.py
boldsign/api_client.py
boldsign/api_response.py
boldsign/configuration.py
boldsign/exceptions.py
boldsign/py.typed
boldsign/rest.py
boldsign/api/__init__.py
boldsign/api/branding_api.py
boldsign/api/contacts_api.py
boldsign/api/custom_field_api.py
boldsign/api/document_api.py
boldsign/api/identity_verification_api.py
boldsign/api/plan_api.py
boldsign/api/sender_identities_api.py
boldsign/api/teams_api.py
boldsign/api/template_api.py
boldsign/api/user_api.py
boldsign/models/__init__.py
boldsign/models/access_code_detail.py
boldsign/models/access_code_details.py
boldsign/models/added.py
boldsign/models/address.py
boldsign/models/attachment_info.py
boldsign/models/audit_trail.py
boldsign/models/authentication_settings.py
boldsign/models/base64_file.py
boldsign/models/behalf_document.py
boldsign/models/behalf_document_records.py
boldsign/models/behalf_of.py
boldsign/models/billing_view_model.py
boldsign/models/brand_created.py
boldsign/models/brand_custom_field_details.py
boldsign/models/branding_message.py
boldsign/models/branding_records.py
boldsign/models/change_recipient.py
boldsign/models/change_team_request.py
boldsign/models/collaboration_settings.py
boldsign/models/conditional_rule.py
boldsign/models/contact_created.py
boldsign/models/contact_details.py
boldsign/models/contact_page_details.py
boldsign/models/contacts_details.py
boldsign/models/contacts_list.py
boldsign/models/create_contact_response.py
boldsign/models/create_sender_identity_request.py
boldsign/models/create_team_request.py
boldsign/models/create_template_request.py
boldsign/models/create_user.py
boldsign/models/custom_domain_settings.py
boldsign/models/custom_field_collection.py
boldsign/models/custom_field_message.py
boldsign/models/custom_form_field.py
boldsign/models/delete_custom_field_reply.py
boldsign/models/document.py
boldsign/models/document_cc.py
boldsign/models/document_cc_details.py
boldsign/models/document_created.py
boldsign/models/document_expiry_settings.py
boldsign-3.0.2.dist-info/LICENSE
boldsign-3.0.2.dist-info/METADATA
boldsign-3.0.2.dist-info/WHEEL
boldsign-3.0.2.dist-info/top_level.txt
boldsign-3.0.2.dist-info/RECORD
